{
  "meta": {
    "name": "Clínica Veterinária Zenvet",
    "slug": "clinica-veterinaria-zenvet",
    "workspace_id": "0ba48cbc-b33f-48c8-b1b1-f505c21c5689",
    "created_at": "2026-04-16",
    "modulo_vendas": true
  },
  "briefing": {
    "identification": {
      "name": "Clínica Veterinária Zenvet",
      "contact_name": "Nathalia Alves",
      "contact_role": "Proprietária e Veterinária",
      "contact_financial": "Kelly (irmã)",
      "segment": "Saúde Animal & Pet Care",
      "annual_revenue": "R$ 653.051,74",
      "monthly_revenue_last": "R$ 81.657,01",
      "monthly_revenue_goal": "R$ 90.000,00",
      "years_in_market": null,
      "location": "Americana, SP",
      "coverage_cities": [
        "Americana",
        "Santa Bárbara d'Oeste",
        "Nova Odessa"
      ],
      "website": "https://clinicazenvet.com.br",
      "instagram": "@clinicazenvet",
      "whatsapp": "(19) 99579-5483",
      "gmb": true,
      "contract_value": "R$ 18.546,00 (6x boleto)",
      "contract_start": "2026-04-15",
      "v4_team": {
        "closer": "Wellington Elias da Silva",
        "executor": "Rafael Corazza",
        "diagnostico": "Leonardo Rosa"
      }
    },
    "product": {
      "main_product": "Consultas veterinárias (rotina, especialista em felinos, dermatológicas), exames hematológicos, vacinas, internação, ultrassom abdominal, radiografia, cirurgias e venda de medicações",
      "ticket": "R$ 500,00 (felinos/especializada pode chegar a R$ 1.000,00)",
      "billing_model": "unico",
      "sales_cycle": "imediato (agendamento no mesmo dia)",
      "active_customers": "1.186 ativos / 1.700 pacientes cadastrados",
      "most_profitable": "Consulta especialista em felinos, internação e cirurgias",
      "growth_potential": "Consulta felinos premium + expansão tutores de cães",
      "mix_atual": "70% tutores de gatos / 30% tutores de cães",
      "services": [
        "Consultas veterinárias de rotina",
        "Consultas especializadas em felinos",
        "Consultas dermatológicas",
        "Exames hematológicos",
        "Vacinação e prevenção",
        "Ultrassom abdominal e radiografia",
        "Internação veterinária",
        "Cirurgias veterinárias",
        "Venda de medicações"
      ]
    },
    "icp": {
      "best_customers": null,
      "not_customers": null,
      "current_profile": "Tutores de pets, majoritariamente classe média, 70% gatos 30% cães",
      "desired_profile": "Classe média a alta, maior consciência sobre medicina preventiva e cuidados contínuos",
      "persona": {
        "name": "Mariana",
        "age": "36 anos",
        "class": "Classe média a média alta",
        "behavior": "Busca prevenção, não apenas urgência. Valoriza confiança técnica e atendimento humanizado e especializado.",
        "channels": [
          "Instagram",
          "Facebook",
          "WhatsApp",
          "Google"
        ],
        "objections": [
          "preço total do tratamento",
          "medo de exames desnecessários",
          "receio de demora",
          "insegurança sobre especialização da clínica"
        ]
      },
      "problems_before": null,
      "results_after": null,
      "churn_reasons": "Concorrência (foram para outro) e lead sumiu sem retorno"
    },
    "competition": {
      "competitors": [
        {
          "name": "Dois hospitais veterinários 24h (mesma avenida)",
          "perceived_differential": "Consulta isca R$ 70, domínio do Google local, retenção forçada do animal até pagamento"
        },
        {
          "name": "Cantinho do Mascote",
          "perceived_differential": "Concorrente regional direto"
        },
        {
          "name": "LM Hospital Veterinário",
          "perceived_differential": "Hospital — maior estrutura"
        },
        {
          "name": "Shopdog",
          "perceived_differential": "Pet shop com serviços agregados"
        },
        {
          "name": "Xodog",
          "perceived_differential": "Concorrente regional"
        }
      ],
      "real_differential": null,
      "why_choose_us": null,
      "competitive_advantage_observed": "Atendimento humanizado para felinos (especialização difícil de replicar), Nathalia especialista em gatos, clientes dos concorrentes buscam segunda opinião na Zenvet, acompanhamento pós-atendimento ativo"
    },
    "brand": {
      "adjectives": null,
      "voice_tone": null,
      "admired_brands": null,
      "current_colors": null,
      "has_logo": true,
      "restrictions": null
    },
    "digital_situation": {
      "paid_traffic": true,
      "platforms": [
        "google_ads",
        "meta_ads"
      ],
      "monthly_investment_total": "R$ 3.200,00",
      "monthly_investment_google": "R$ 2.400,00",
      "monthly_investment_meta": "R$ 800,00",
      "current_results": "72 leads → 12 agendamentos (16,6% conversão). Taxa de show ~100%. CAC atual: R$ 266,00.",
      "issues": "Meta Ads com links quebrados (erro 404). Google Ads invisível para termos-chave. Sem Pixel Facebook. Sem Google Tag.",
      "crm": null,
      "lead_sources": "Indicação de clientes atuais, anúncios pagos (Google e Meta), redes sociais orgânicas",
      "conversion_rate": "16,6% (lead → agendamento)",
      "biggest_pain": "Falta de leads qualificados, ausência de rastreamento (sem pixel/tags), LP sem conversão, sem CRM, agência anterior sem transparência",
      "monthly_posts_frequency": "Várias vezes por semana",
      "content_type": "Conteúdo educativo",
      "active_channels": [
        "Instagram",
        "Facebook",
        "Google Meu Negócio"
      ]
    },
    "accesses": {
      "meta_business": false,
      "google_ads": false,
      "google_analytics": false,
      "google_search_console": false,
      "instagram_admin": false,
      "website_admin": false,
      "crm": false,
      "gmb": true,
      "whatsapp_business": true
    },
    "sales_module": {
      "active_sellers": "1 (Loíse — recepcionista/comercial)",
      "sales_process": "Atendimento reativo via WhatsApp. Qualificação automática inicial: cão ou gato? Domicílio ou clínica?",
      "objections": [
        "Preço vs concorrência",
        "Lead some sem retorno"
      ],
      "conversion_rate": "16,6% lead → agendamento / ~100% agendamento → atendimento",
      "sales_cycle": "Imediato (mesmo dia ou próximos dias)",
      "has_scripts": false,
      "needs": "Treinamento consultivo para Loíse, CRM, script por tipo de serviço, follow-up estruturado"
    }
  },
  "research": {
    "fetched_at": null
  },
  "connectors": {
    "fetched_at": "2026-04-18T15:30:00Z",
    "period": {
      "start": "2025-01-01",
      "end": "2026-04-18"
    },
    "google_ads": {
      "integration_name": "VET519 - Clínica Zen Vet",
      "total_campaigns": 15,
      "total_cost": 13975.1,
      "total_clicks": 11008,
      "total_impressions": 300869,
      "total_conversions": 1225.0,
      "avg_cpa": 11.41,
      "avg_ctr": 3.66,
      "campaigns": [
        {
          "name": "[Sc] - [Pesquisa] - [13/03]",
          "type": "SEARCH",
          "status": "ENABLED",
          "budget_daily": 80.0,
          "cost": 1675.51,
          "clicks": 389,
          "impressions": 5946,
          "conversions": 63.0,
          "ctr": 6.54,
          "cpa": 26.6
        },
        {
          "name": "flyvet.search - Geral",
          "type": "SEARCH",
          "status": "PAUSED",
          "budget_daily": 78.0,
          "cost": 6212.79,
          "clicks": 2254,
          "impressions": 46663,
          "conversions": 473.54,
          "ctr": 4.83,
          "cpa": 13.12
        },
        {
          "name": "flyvet.pmax - Geral Nova",
          "type": "PERFORMANCE_MAX",
          "status": "PAUSED",
          "budget_daily": 5.0,
          "cost": 352.47,
          "clicks": 1344,
          "impressions": 44879,
          "conversions": 198.96,
          "ctr": 2.99,
          "cpa": 1.77
        },
        {
          "name": "flyvet.gdm - vacinação",
          "type": "DEMAND_GEN",
          "status": "PAUSED",
          "budget_daily": 5.0,
          "cost": 917.48,
          "clicks": 1752,
          "impressions": 66043,
          "conversions": 266.98,
          "ctr": 2.65,
          "cpa": 3.44
        },
        {
          "name": "flyvet.search - Serviços",
          "type": "SEARCH",
          "status": "PAUSED",
          "budget_daily": 12.0,
          "cost": 1426.97,
          "clicks": 412,
          "impressions": 7812,
          "conversions": 83.5,
          "ctr": 5.27,
          "cpa": 17.09
        },
        {
          "name": "C01 - CONSULTIVA | SEARCH [21/03/2025] MAX CLIQUES",
          "type": "SEARCH",
          "status": "PAUSED",
          "budget_daily": 30.0,
          "cost": 1386.77,
          "clicks": 1006,
          "impressions": 29349,
          "conversions": 44.0,
          "ctr": 3.43,
          "cpa": 31.52
        },
        {
          "name": "[OFF_ROS] Veterinária em Americana",
          "type": "SMART",
          "status": "PAUSED",
          "budget_daily": 40.0,
          "cost": 938.1,
          "clicks": 2542,
          "impressions": 71439,
          "conversions": 23.0,
          "ctr": 3.56,
          "cpa": 40.79
        },
        {
          "name": "[OFF] C02 - CONSULTIVA | PMAX - CATEGORIZADA",
          "type": "PERFORMANCE_MAX",
          "status": "PAUSED",
          "budget_daily": 5.0,
          "cost": 371.47,
          "clicks": 886,
          "impressions": 18206,
          "conversions": 59.0,
          "ctr": 4.87,
          "cpa": 6.3
        },
        {
          "name": "flyvet.search - Serviços Nova",
          "type": "SEARCH",
          "status": "PAUSED",
          "budget_daily": 10.0,
          "cost": 107.4,
          "clicks": 85,
          "impressions": 1527,
          "conversions": 1.0,
          "ctr": 5.57,
          "cpa": 107.4
        },
        {
          "name": "flyvet.search - Nova Institucional",
          "type": "SEARCH",
          "status": "PAUSED",
          "budget_daily": 5.0,
          "cost": 172.07,
          "clicks": 113,
          "impressions": 1279,
          "conversions": 5.0,
          "ctr": 8.84,
          "cpa": 34.41
        },
        {
          "name": "flyvet.search - felinos",
          "type": "SEARCH",
          "status": "PAUSED",
          "budget_daily": 5.0,
          "cost": 106.08,
          "clicks": 42,
          "impressions": 661,
          "conversions": 0.0,
          "ctr": 6.35,
          "cpa": null
        },
        {
          "name": "flyvet.gdm - Reconhecimento",
          "type": "DEMAND_GEN",
          "status": "PAUSED",
          "budget_daily": 5.0,
          "cost": 44.36,
          "clicks": 30,
          "impressions": 1734,
          "conversions": 2.02,
          "ctr": 1.73,
          "cpa": 21.96
        },
        {
          "name": "flyvet.pmax - Geral",
          "type": "PERFORMANCE_MAX",
          "status": "PAUSED",
          "budget_daily": 5.0,
          "cost": 79.92,
          "clicks": 67,
          "impressions": 2854,
          "conversions": 1.0,
          "ctr": 2.35,
          "cpa": 79.92
        },
        {
          "name": "flyvet.search - Institucional",
          "type": "SEARCH",
          "status": "PAUSED",
          "budget_daily": 5.0,
          "cost": 92.43,
          "clicks": 54,
          "impressions": 1905,
          "conversions": 4.0,
          "ctr": 2.83,
          "cpa": 23.11
        },
        {
          "name": "[OFF] C03 - CONSULTIVA | SEARCH - CATEGORIZADA",
          "type": "SEARCH",
          "status": "PAUSED",
          "budget_daily": 5.0,
          "cost": 91.28,
          "clicks": 32,
          "impressions": 572,
          "conversions": 0.0,
          "ctr": 5.59,
          "cpa": null
        }
      ]
    },
    "facebook_ads": {
      "integration_name": "Nathália H. Alves",
      "total_campaigns": 15,
      "total_spend": 3472.63,
      "total_impressions": 343910,
      "total_clicks": 2603,
      "total_reach": 270330,
      "avg_cpm": 10.1,
      "avg_ctr": 0.76,
      "campaigns": [
        {
          "name": "[SC] - [Engajamento_Mensagens] - [13/03]",
          "objective": "OUTCOME_ENGAGEMENT",
          "spend": 974.37,
          "impressions": 95436,
          "clicks": 1262,
          "reach": 58923,
          "cpm": 10.21
        },
        {
          "name": "[OFF] C01 [04/04/2025] - CONSULTIVA | ENGAJAMENTO - WHATSAPP",
          "objective": "OUTCOME_ENGAGEMENT",
          "spend": 747.78,
          "impressions": 43877,
          "clicks": 365,
          "reach": 31116,
          "cpm": 17.04
        },
        {
          "name": "Publicação do Instagram: Conheça um pouco mais...",
          "objective": "MESSAGES",
          "spend": 547.74,
          "impressions": 33576,
          "clicks": 248,
          "reach": 28397,
          "cpm": 16.31
        },
        {
          "name": "Publicação do Instagram: Primeira dose da vacina...",
          "objective": "MESSAGES",
          "spend": 250.94,
          "impressions": 13928,
          "clicks": 154,
          "reach": 10724,
          "cpm": 18.02
        },
        {
          "name": "Post do Instagram: 💜🐾 Seu pet merece...",
          "objective": "MESSAGES",
          "spend": 192.37,
          "impressions": 12653,
          "clicks": 85,
          "reach": 11137,
          "cpm": 15.2
        },
        {
          "name": "Publicação do Instagram: 💜🐾 Seu pet merece...",
          "objective": "MESSAGES",
          "spend": 146.07,
          "impressions": 6692,
          "clicks": 76,
          "reach": 6261,
          "cpm": 21.83
        },
        {
          "name": "Instagram post: 💜🐾 Seu pet merece...",
          "objective": "MESSAGES",
          "spend": 139.65,
          "impressions": 8257,
          "clicks": 73,
          "reach": 6159,
          "cpm": 16.91
        },
        {
          "name": "[OFF] C03 [14/05/2024] - AQUISIÇÃO | RECONHECIMENTO - IG",
          "objective": "OUTCOME_AWARENESS",
          "spend": 121.96,
          "impressions": 105081,
          "clicks": 81,
          "reach": 98549,
          "cpm": 1.16
        },
        {
          "name": "Instagram post: Um novo conceito em atendimento...",
          "objective": "MESSAGES",
          "spend": 95.22,
          "impressions": 5726,
          "clicks": 50,
          "reach": 4540,
          "cpm": 16.63
        },
        {
          "name": "Publicação do Instagram: A Dra. Nathalia Alves é...",
          "objective": "MESSAGES",
          "spend": 71.04,
          "impressions": 4618,
          "clicks": 20,
          "reach": 3156,
          "cpm": 15.38
        },
        {
          "name": "[OFF] C04 [24/05/2025] - CONSULTIVA | LEADS - NATIVO",
          "objective": "OUTCOME_LEADS",
          "spend": 65.92,
          "impressions": 3985,
          "clicks": 43,
          "reach": 3327,
          "cpm": 16.54
        },
        {
          "name": "Atendimento a domicílio",
          "objective": "OUTCOME_ENGAGEMENT",
          "spend": 49.91,
          "impressions": 3855,
          "clicks": 56,
          "reach": 2979,
          "cpm": 12.95
        },
        {
          "name": "[SC] - [CBO] Mensagens [13/04]",
          "objective": "OUTCOME_ENGAGEMENT",
          "spend": 35.76,
          "impressions": 3263,
          "clicks": 49,
          "reach": 2436,
          "cpm": 10.96
        },
        {
          "name": "Publicação do Instagram: Sem estresse! Evite o...",
          "objective": "MESSAGES",
          "spend": 19.98,
          "impressions": 1304,
          "clicks": 11,
          "reach": 1084,
          "cpm": 15.32
        },
        {
          "name": "[OFF] C02 [11/04/2025] - AQUISIÇÃO | TRAFEGO - IG",
          "objective": "LINK_CLICKS",
          "spend": 13.92,
          "impressions": 1659,
          "clicks": 30,
          "reach": 1542,
          "cpm": 8.39
        }
      ]
    }
  },
  "progress": {
    "current_week": 1,
    "skills": {
      "ee-s1-diagnostico-maturidade": {
        "status": "completed",
        "checkpoint": 1,
        "started_at": "2026-04-16",
        "completed_at": "2026-04-16"
      },
      "ee-s1-swot": {
        "status": "completed",
        "checkpoint": 1,
        "started_at": "2026-04-18",
        "completed_at": "2026-04-18",
        "version": 1
      },
      "ee-s1-persona-icp": {
        "status": "completed",
        "checkpoint": 0,
        "started_at": null,
        "completed_at": "2026-04-18",
        "version": 1
      },
      "ee-s1-auditoria-comunicacao": {
        "status": "completed",
        "checkpoint": 1,
        "started_at": "2026-04-18",
        "completed_at": "2026-04-18",
        "version": 1
      },
      "ee-s2-pesquisa-mercado": {
        "status": "pending",
        "checkpoint": 0,
        "started_at": null,
        "completed_at": null
      },
      "ee-s2-posicionamento": {
        "status": "pending",
        "checkpoint": 0,
        "started_at": null,
        "completed_at": null
      },
      "ee-s2-diagnostico-midia": {
        "status": "completed",
        "checkpoint": 1,
        "started_at": "2026-04-18",
        "completed_at": "2026-04-18",
        "version": 1
      },
      "ee-s2-diagnostico-criativos": {
        "status": "pending",
        "checkpoint": 0,
        "started_at": null,
        "completed_at": null
      },
      "ee-s2-diagnostico-cro": {
        "status": "pending",
        "checkpoint": 0,
        "started_at": null,
        "completed_at": null
      },
      "ee-s3-identidade-visual": {
        "status": "pending",
        "checkpoint": 0,
        "started_at": null,
        "completed_at": null
      },
      "ee-s3-brandbook": {
        "status": "pending",
        "checkpoint": 0,
        "started_at": null,
        "completed_at": null
      },
      "ee-s3-landing-page": {
        "status": "pending",
        "checkpoint": 0,
        "started_at": null,
        "completed_at": null
      },
      "ee-s3-copy-anuncios": {
        "status": "pending",
        "checkpoint": 0,
        "started_at": null,
        "completed_at": null
      },
      "ee-s3-criativos-anuncios": {
        "status": "pending",
        "checkpoint": 0,
        "started_at": null,
        "completed_at": null
      },
      "ee-s3-crm-setup": {
        "status": "pending",
        "checkpoint": 0,
        "started_at": null,
        "completed_at": null
      },
      "ee-s3-forecast-midia": {
        "status": "pending",
        "checkpoint": 0,
        "started_at": null,
        "completed_at": null
      },
      "ee-s3-gmb-otimizacao": {
        "status": "pending",
        "checkpoint": 0,
        "started_at": null,
        "completed_at": null
      },
      "ee-s4-diagnostico-comercial": {
        "status": "pending",
        "checkpoint": 0,
        "started_at": null,
        "completed_at": null
      },
      "ee-s4-cliente-oculto": {
        "status": "pending",
        "checkpoint": 0,
        "started_at": null,
        "completed_at": null
      },
      "ee-s5-scripts-sdr": {
        "status": "pending",
        "checkpoint": 0,
        "started_at": null,
        "completed_at": null
      },
      "ee-s5-sdr-ia-config": {
        "status": "pending",
        "checkpoint": 0,
        "started_at": null,
        "completed_at": null
      }
    }
  },
  "history": [
    {
      "ts": "2026-04-16T00:00:00Z",
      "skill": "ee-novo-cliente",
      "checkpoint": 0,
      "decision": "Cliente cadastrado. Briefing extraído da documentação completa (formulário V4MOS, diagnóstico, rollout, plano de ROI e kickoff). Campos de marca e ICP qualitativo (adjetivos, tom de voz, melhores clientes, restrições) ficaram null — operador não tem as informações. Coletar com Nathalia durante Semana 1."
    },
    {
      "ts": "2026-04-16T00:00:00Z",
      "skill": "ee-s1-diagnostico-maturidade",
      "checkpoint": 1,
      "decision": "Score geral 21/100 (Crítico). Digital ativamente destrói valor. 5 prioridades definidas: tracking, Meta Ads, Google Ads, régua de reativação base 1.700 pacientes, LP felinos. Aprovado pelo operador."
    },
    {
      "ts": "2026-04-18T20:00:00Z",
      "skill": "ee-s1-persona-icp",
      "action": "completed",
      "note": "ICP e Persona aprovados. Segmento principal: tutoras de gatos 30-45 anos, classe média-alta, Americana/SBO/Nova Odessa. Mensagem-chave escolhida: opção emocional ('Seu gato merece uma veterinária que entende de felinos — não de bicho em geral.'). ICP secundário criado para tutores de cães com mensagem separada focada em agilidade e transparência."
    },
    {
      "ts": "2026-04-18T21:00:00Z",
      "skill": "ee-s1-swot",
      "action": "completed",
      "note": "SWOT aprovada. 6F + 6W + 6O + 5A. Jogada principal: ocupar território 'especialista em felinos de Americana' antes dos concorrentes, eliminando hemorragias digitais (tracking zero, Meta Ads link quebrado) e construindo ativos proprietários (CRM, conteúdo educativo, GMB). 7 ações prioritárias com Gantt roadmap S1-S5. Ações mais urgentes: tracking + Meta Ads corrigidos na S1."
    },
    {
      "ts": "2026-04-18T22:00:00Z",
      "skill": "ee-s1-auditoria-comunicacao",
      "action": "completed",
      "note": "Auditoria aprovada. Score médio 35/100 (Crítico). 3 hemorragias: Meta Ads 404 (R$800/mês destruídos), zero tracking, mensagem-chave felinos ausente em todos os canais. Instagram é o único ponto positivo (ativo, educativo). 5 Quick Wins definidos para execução imediata: corrigir link Meta, instalar Pixel/GTM, atualizar bio Instagram, post GMB, mensagem ausência WhatsApp."
    },
    {
      "ts": "2026-04-18T23:00:00Z",
      "skill": "ee-s2-diagnostico-midia",
      "action": "completed",
      "note": "Diagnóstico aprovado com dados V4MOS reais. CAC R$266 (alvo: R$120). Meta Ads 100% desperdiçado (links 404 + objetivo errado). Google com 14/15 campanhas pausadas incluindo 3 de CPA R$1,77–R$13. Audiência 56% feminina confirma ICP. Segunda e Sábado são dias de pico. Keywords de domicílio (CTR 14,3%) e felinos (CPA R$1,65) subexploradas. 8 ações priorizadas para 30 dias. Meta 90d: CPL R$44 → R$22, CAC R$266 → R$120."
    }
  ]
}